abaqus2dyna/__init__.py
abaqus2dyna/__main__.py
abaqus2dyna/_version.py
abaqus2dyna/test/__init__.py
abaqus2dyna/test/test_basic.py
abaqus2dyna-0.0.5.dist-info/METADATA
abaqus2dyna-0.0.5.dist-info/RECORD
abaqus2dyna-0.0.5.dist-info/WHEEL
abaqus2dyna-0.0.5.dist-info/entry_points.txt
abaqus2dyna-0.0.5.dist-info/top_level.txt
