Metadata-Version: 2.1
Name: abaqus2dyna
Version: 0.0.5
Summary: Translator from Abaqus input files to LS-DYNA input files
Home-page: https://github.com/tbhartman/abaqus2dyna
Author: Tim Hartman
Author-email: tbhartman@gmail.com
License: MIT
Keywords: abaqus ls-dyna dyna
Platform: UNKNOWN
Classifier: Development Status :: 3 - Alpha
Classifier: Topic :: Utilities
Classifier: License :: OSI Approved :: MIT License
Provides-Extra: test
Requires-Dist: numpy
Provides-Extra: test
Requires-Dist: behave; extra == 'test'
Requires-Dist: pytest; extra == 'test'
Requires-Dist: pytest-cov; extra == 'test'
Requires-Dist: coverage; extra == 'test'
